hostphot/__init__.py
hostphot/_constants.py
hostphot/_version.py
hostphot/surveys_utils.py
hostphot/utils.py
hostphot/cutouts/__init__.py
hostphot/cutouts/des.py
hostphot/cutouts/downloads.py
hostphot/cutouts/galex.py
hostphot/cutouts/hst.py
hostphot/cutouts/jwst.py
hostphot/cutouts/legacysurvey.py
hostphot/cutouts/panstarrs.py
hostphot/cutouts/sdss.py
hostphot/cutouts/skymapper.py
hostphot/cutouts/spitzer.py
hostphot/cutouts/splus.py
hostphot/cutouts/twomass.py
hostphot/cutouts/ukidss.py
hostphot/cutouts/vista.py
hostphot/cutouts/wise.py
hostphot/filters/AAA_README
hostphot/filters/config.txt
hostphot/filters/filters.yml
hostphot/filters/2MASS/2MASS_H.dat
hostphot/filters/2MASS/2MASS_J.dat
hostphot/filters/2MASS/2MASS_Ks.dat
hostphot/filters/2MASS/AAA_README
hostphot/filters/DES/AAA_README
hostphot/filters/DES/DES_Y.dat
hostphot/filters/DES/DES_g.dat
hostphot/filters/DES/DES_i.dat
hostphot/filters/DES/DES_r.dat
hostphot/filters/DES/DES_z.dat
hostphot/filters/GALEX/AAA_README
hostphot/filters/GALEX/GALEX_FUV.dat
hostphot/filters/GALEX/GALEX_NUV.dat
hostphot/filters/HST/IR_err.txt
hostphot/filters/HST/UVIS1_err.txt
hostphot/filters/HST/UVIS2_err.txt
hostphot/filters/HST/ir_aper_corrections.csv
hostphot/filters/HST/wfc3uvis1_aper_007_syn.csv
hostphot/filters/HST/wfc3uvis2_aper_007_syn.csv
hostphot/filters/HST/ACS_WFC/ACS_WFC_F435W.dat
hostphot/filters/HST/ACS_WFC/ACS_WFC_F475W.dat
hostphot/filters/HST/ACS_WFC/ACS_WFC_F502N.dat
hostphot/filters/HST/ACS_WFC/ACS_WFC_F550M.dat
hostphot/filters/HST/ACS_WFC/ACS_WFC_F555W.dat
hostphot/filters/HST/ACS_WFC/ACS_WFC_F606W.dat
hostphot/filters/HST/ACS_WFC/ACS_WFC_F625W.dat
hostphot/filters/HST/ACS_WFC/ACS_WFC_F658N.dat
hostphot/filters/HST/ACS_WFC/ACS_WFC_F660N.dat
hostphot/filters/HST/ACS_WFC/ACS_WFC_F775W.dat
hostphot/filters/HST/ACS_WFC/ACS_WFC_F814W.dat
hostphot/filters/HST/ACS_WFC/ACS_WFC_F850LP.dat
hostphot/filters/HST/ACS_WFC/ACS_WFC_F892N.dat
hostphot/filters/HST/ACS_WFC/ACS_WFC_FR1016N.dat
hostphot-3.1.1.dist-info/licenses/LICENSE
hostphot-3.1.1.dist-info/METADATA
hostphot-3.1.1.dist-info/WHEEL
hostphot-3.1.1.dist-info/top_level.txt
hostphot-3.1.1.dist-info/RECORD
