Metadata-Version: 2.4
Name: hostphot
Version: 3.1.1
Summary: Global and local photometry of galaxies hosting supernovae or other transients
Home-page: https://github.com/temuller/hostphot
Author: Tomás Enrique Müller-Bravo and Lluís Galbany
Author-email: t.e.muller-bravo@ice.csic.es
License: MIT
Classifier: Programming Language :: Python :: 3
Classifier: License :: OSI Approved :: MIT License
Classifier: Operating System :: OS Independent
Requires-Python: >=3.9
License-File: LICENSE
Requires-Dist: pip
Requires-Dist: numpy
Requires-Dist: pandas
Requires-Dist: matplotlib
Requires-Dist: aplpy
Requires-Dist: python-dotenv
Requires-Dist: astropy
Requires-Dist: reproject
Requires-Dist: photutils
Requires-Dist: astroquery
Requires-Dist: extinction
Requires-Dist: sfdmap2
Requires-Dist: mocpy
Requires-Dist: pyvo
Requires-Dist: sep
Requires-Dist: pytest
Dynamic: author
Dynamic: author-email
Dynamic: classifier
Dynamic: description
Dynamic: description-content-type
Dynamic: home-page
Dynamic: license
Dynamic: license-file
Dynamic: requires-dist
Dynamic: requires-python
Dynamic: summary
